senzing_grpc/__init__.py
senzing_grpc/szabstractfactory.py
senzing_grpc/szconfig.py
senzing_grpc/szconfigmanager.py
senzing_grpc/szdiagnostic.py
senzing_grpc/szengine.py
senzing_grpc/szhelpers.py
senzing_grpc/szproduct.py
senzing_grpc-0.5.13.dist-info/licenses/LICENSE
senzing_grpc-0.5.13.dist-info/METADATA
senzing_grpc-0.5.13.dist-info/WHEEL
senzing_grpc-0.5.13.dist-info/top_level.txt
senzing_grpc-0.5.13.dist-info/RECORD
