Metadata-Version: 2.4
Name: senzing_grpc
Version: 0.5.13
Summary: Senzing Python SDK over gRPC
Home-page: https://github.com/senzing-garage/sz-sdk-python-grpc
Author: senzing
Author-email: support@senzing.com
License: Apache 2
Project-URL: Bug Tracker, https://github.com/senzing-garage/sz-sdk-python-grpc/issues
Classifier: Programming Language :: Python :: 3
Classifier: License :: OSI Approved :: Apache Software License
Classifier: Operating System :: OS Independent
Requires-Python: >=3.9
License-File: LICENSE
Requires-Dist: grpcio>=1.74.0
Requires-Dist: protobuf>=6.31.1
Requires-Dist: senzing<5.0.0,>=4.0.0
Requires-Dist: senzing-grpc-protobuf>=0.0.3
Dynamic: license-file
